detectk_detectors/__init__.py
detectk_detectors/mad.py
detectk_detectors/missing_data.py
detectk_detectors/threshold.py
detectk_detectors/zscore.py
detectk_detectors-0.2.0.dist-info/METADATA
detectk_detectors-0.2.0.dist-info/WHEEL
detectk_detectors-0.2.0.dist-info/top_level.txt
detectk_detectors-0.2.0.dist-info/RECORD
