Metadata-Version: 2.4
Name: detectk-detectors
Version: 0.2.0
Summary: Core detectors for DetectK: threshold, statistical (MAD, Z-score, IQR)
Author-email: Alexei Veselov <alexeiveselov92@gmail.com>
Keywords: detectk,anomaly-detection,detectors,threshold,statistics
Classifier: Development Status :: 3 - Alpha
Classifier: Intended Audience :: Developers
Classifier: Topic :: System :: Monitoring
Classifier: Programming Language :: Python :: 3.10
Classifier: Programming Language :: Python :: 3.11
Classifier: Programming Language :: Python :: 3.12
Requires-Python: >=3.10
Requires-Dist: detectk>=0.1.0
Requires-Dist: pandas>=2.0.0
Requires-Dist: numpy>=1.24.0
Provides-Extra: dev
Requires-Dist: pytest>=7.0; extra == "dev"
Requires-Dist: pytest-cov>=4.0; extra == "dev"
Requires-Dist: black>=23.0; extra == "dev"
Requires-Dist: ruff>=0.1.0; extra == "dev"
Requires-Dist: mypy>=1.0; extra == "dev"
